furtheredge/__init__.py
furtheredge/abstracted_packages.py
furtheredge/universal_life_module.py
furtheredge/modules/__init__.py
furtheredge/modules/validator_dfs.py
furtheredge/modules/model_point_generator/__init__.py
furtheredge/modules/model_point_generator/model_point_generator.py
furtheredge/modules/model_point_generator/policies_refinement.py
furtheredge/modules/universal_life/__init__.py
furtheredge/modules/universal_life/merge_all_df.py
furtheredge/modules/universal_life/required_data_calculation.py
furtheredge/modules/universal_life/run.py
furtheredge/modules/universal_life/tools.py
furtheredge/modules/universal_life/sub_modules/_1_duration.py
furtheredge/modules/universal_life/sub_modules/_2_reserve.py
furtheredge/modules/universal_life/sub_modules/_2_reserve_old.py
furtheredge/modules/universal_life/sub_modules/_3_proba.py
furtheredge/modules/universal_life/sub_modules/_4_prospective.py
furtheredge/modules/universal_life/sub_modules/__init__.py
inputs/__init__.py
inputs/product.csv
inputs/ri_rates.csv
inputs/tech_assumptions.csv
inputs/wop_rates.csv
furtheredge-0.1.3.dist-info/METADATA
furtheredge-0.1.3.dist-info/WHEEL
furtheredge-0.1.3.dist-info/top_level.txt
furtheredge-0.1.3.dist-info/RECORD
