Metadata-Version: 2.1
Name: furtheredge
Version: 0.1.3
Summary: furtheredge-modules
Author: Novacture
Author-email: amine.zemni@novacture.com
Classifier: Programming Language :: Python :: 3
Requires-Dist: numpy
Requires-Dist: pandas ==2.2.2
Requires-Dist: pytest
